observeit/__init__.py
observeit/decorators.py
observeit/exceptions.py
observeit/bin/__init__.py
observeit/bin/observeit_cli.py
observeit/clients/__init__.py
observeit/clients/observeit_base_client.py
observeit/clients/observeit_login_client.py
observeit/clients/observeit_oauth_client.py
observeit/controls/__init__.py
observeit/controls/application_controls.py
observeit/controls/application_controls.py~
observeit/controls/list_controls.py
observeit/controls/list_controls.py~
observeit/controls/report_controls.py
observeit/controls/report_controls.py~
observeit/controls/session_controls.py
observeit/controls/session_controls.py~
observeit-1.0.0.dist-info/LICENSE.txt
observeit-1.0.0.dist-info/METADATA
observeit-1.0.0.dist-info/RECORD
observeit-1.0.0.dist-info/WHEEL
observeit-1.0.0.dist-info/entry_points.txt
observeit-1.0.0.dist-info/top_level.txt
