Metadata-Version: 2.1
Name: observeit
Version: 1.0.0
Summary: ObserveIT REST Wrapper and CLI
Home-page: https://bitbucket.org/observeit/observeit-py
Author: ObserveIT Inc
Author-email: integrations@observeit.com
License: Apache2
Platform: any
Classifier: Programming Language :: Python
Classifier: License :: OSI Approved :: Apache Software License
Classifier: Programming Language :: Python :: 3
Classifier: Programming Language :: Python :: 2.7
Classifier: Operating System :: OS Independent
Classifier: Natural Language :: English
Requires-Dist: requests
Requires-Dist: requests-oauthlib
Requires-Dist: click
Requires-Dist: numpy
Requires-Dist: opencv-python
